setup.py
AstroLabels.egg-info/PKG-INFO
AstroLabels.egg-info/SOURCES.txt
AstroLabels.egg-info/dependency_links.txt
AstroLabels.egg-info/top_level.txt
astrolabels/__init__.py
astrolabels/astrolabels.py
astrolabels/tests/__init__.py
astrolabels/tests/test_astrolabels.py