Metadata-Version: 1.1
Name: AstroLabels
Version: 0.1
Summary: AstroLabels
Home-page: http://github.com/jesford/AstroLabels
Author: Jes Ford
Author-email: jesford@uw.edu
License: MIT
Download-URL: http://github.com/jesford/AstroLabels
Platform: UNKNOWN
Classifier: Intended Audience :: Science/Research
Classifier: License :: OSI Approved :: MIT License
Classifier: Natural Language :: English
Classifier: Programming Language :: Python :: 2.7
Classifier: Programming Language :: Python :: 3.4
Classifier: Programming Language :: Python :: 3.5
